ckanext/__init__.py
ckanext/event_audit/__init__.py
ckanext/event_audit/cli.py
ckanext/event_audit/collection.py
ckanext/event_audit/config.py
ckanext/event_audit/const.py
ckanext/event_audit/helpers.py
ckanext/event_audit/interfaces.py
ckanext/event_audit/model.py
ckanext/event_audit/plugin.py
ckanext/event_audit/types.py
ckanext/event_audit/utils.py
ckanext/event_audit/views.py
ckanext/event_audit/exporters/__init__.py
ckanext/event_audit/exporters/base.py
ckanext/event_audit/exporters/csv.py
ckanext/event_audit/exporters/json.py
ckanext/event_audit/exporters/tsv.py
ckanext/event_audit/exporters/xlsx.py
ckanext/event_audit/listeners/__init__.py
ckanext/event_audit/listeners/api.py
ckanext/event_audit/listeners/database.py
ckanext/event_audit/logic/__init__.py
ckanext/event_audit/logic/validators.py
ckanext/event_audit/migration/event_audit/alembic.ini
ckanext/event_audit/migration/event_audit/env.py
ckanext/event_audit/migration/event_audit/script.py.mako
ckanext/event_audit/migration/event_audit/versions/001_9256fa265b84_create_event_table.py
ckanext/event_audit/repositories/__init__.py
ckanext/event_audit/repositories/base.py
ckanext/event_audit/repositories/cloudwatch.py
ckanext/event_audit/repositories/postgres.py
ckanext/event_audit/repositories/redis.py
ckanext/event_audit/templates/event_audit/config.html
ckanext/event_audit/templates/event_audit/event_audit_list.html
ckanext/event_audit/tests/__init__.py
ckanext/event_audit/tests/conftest.py
ckanext/event_audit/tests/test_cli.py
ckanext/event_audit/tests/test_config.py
ckanext/event_audit/tests/test_interface.py
ckanext/event_audit/tests/test_types.py
ckanext/event_audit/tests/test_utils.py
ckanext/event_audit/tests/exporters/test_csv.py
ckanext/event_audit/tests/exporters/test_json.py
ckanext/event_audit/tests/exporters/test_tsv.py
ckanext/event_audit/tests/exporters/test_xlsx.py
ckanext/event_audit/tests/listeners/test_api.py
ckanext/event_audit/tests/listeners/test_model.py
ckanext_event_audit-1.2.14.dist-info/licenses/LICENSE
ckanext_event_audit-1.2.14.dist-info/METADATA
ckanext_event_audit-1.2.14.dist-info/WHEEL
ckanext_event_audit-1.2.14.dist-info/entry_points.txt
ckanext_event_audit-1.2.14.dist-info/top_level.txt
ckanext_event_audit-1.2.14.dist-info/RECORD
