Metadata-Version: 2.4
Name: ckanext-event-audit
Version: 1.2.14
Author-email: DataShades <datashades@linkdigital.com.au>, Oleksandr Cherniavskyi <mutantsan@gmail.com>
License: GNU AFFERO GENERAL PUBLIC LICENSE
Project-URL: Homepage, https://github.com/DataShades/ckanext-event-audit
Project-URL: Documentation, https://datashades.github.io/ckanext-event-audit/
Keywords: CKAN
Classifier: Development Status :: 4 - Beta
Classifier: License :: OSI Approved :: GNU Affero General Public License v3 or later (AGPLv3+)
Classifier: Programming Language :: Python :: 3.8
Classifier: Programming Language :: Python :: 3.9
Classifier: Programming Language :: Python :: 3.10
License-File: LICENSE
Requires-Dist: pydantic<3.0.0,>=2.3.0
Requires-Dist: boto3<2.0.0,>=1.28.35
Requires-Dist: openpyxl<4.0.0,>=3.1.2
Provides-Extra: dev
Requires-Dist: boto3-stubs[logs]<2.0.0,>=1.35.0; extra == "dev"
Requires-Dist: pytest-ckan; extra == "dev"
Requires-Dist: mkdocs<1.7,>=1.6.1; extra == "dev"
Dynamic: license-file
